[
  {
    "id": "1",
    "type": "image",
    "front": "/game-images/img1.jpg",
    "back": "נטלי",
    "listId": "h1",
    "bucket": 1,
    "starred": false
  },
  {
    "id": "2",
    "type": "image",
    "front": "/game-images/img2.jpg",
    "back": "תיאדור",
    "listId": "h1",
    "bucket": 1,
    "starred": false
  },
  {
    "id": "3",
    "type": "image",
    "front": "/game-images/img3.jpg",
    "back": "אביטל",
    "listId": "h1",
    "bucket": 1,
    "starred": false
  },
  {
    "id": "4",
    "type": "image",
    "front": "/game-images/img4.jpg",
    "back": "בנימין",
    "listId": "h1",
    "bucket": 1,
    "starred": false
  },
  {
    "id": "5",
    "type": "image",
    "front": "/game-images/img5.jpg",
    "back": "קרינה",
    "listId": "h1",
    "bucket": 1,
    "starred": false
  },
  {
    "id": "6",
    "type": "image",
    "front": "/game-images/img6.jpg",
    "back": "אהרון",
    "listId": "h1",
    "bucket": 1,
    "starred": false
  },
  {
    "id": "7",
    "type": "image",
    "front": "/game-images/img7.jpg",
    "back": "גבריאל",
    "listId": "h1",
    "bucket": 1,
    "starred": false
  },
  {
    "id": "8",
    "type": "image",
    "front": "/game-images/img8.jpg",
    "back": "חיים",
    "listId": "h1",
    "bucket": 1,
    "starred": false
  },
  {
    "id": "9",
    "type": "image",
    "front": "/game-images/img9.jpg",
    "back": "איתמר",
    "listId": "h1",
    "bucket": 1,
    "starred": false
  },
  {
    "id": "10",
    "type": "image",
    "front": "/game-images/img10.jpg",
    "back": "מיאה",
    "listId": "h1",
    "bucket": 1,
    "starred": false
  },
  {
    "id": "11",
    "type": "image",
    "front": "/game-images/img11.jpg",
    "back": "שוהם",
    "listId": "h1",
    "bucket": 1,
    "starred": false
  },
  {
    "id": "12",
    "type": "image",
    "front": "/game-images/img12.jpg",
    "back": "דניאל",
    "listId": "h1",
    "bucket": 1,
    "starred": false
  },
  {
    "id": "13",
    "type": "image",
    "front": "/game-images/img13.jpg",
    "back": "נועם",
    "listId": "h1",
    "bucket": 1,
    "starred": false
  },
  {
    "id": "14",
    "type": "image",
    "front": "/game-images/img14.jpg",
    "back": "מיכאל",
    "listId": "h1",
    "bucket": 1,
    "starred": false
  },
  {
    "id": "15",
    "type": "image",
    "front": "/game-images/img15.jpg",
    "back": "ארטמי",
    "listId": "h1",
    "bucket": 1,
    "starred": false
  },
  {
    "id": "16",
    "type": "image",
    "front": "/game-images/img16.jpg",
    "back": "דרינה",
    "listId": "h1",
    "bucket": 1,
    "starred": false
  },
  {
    "id": "17",
    "type": "image",
    "front": "/game-images/img17.jpg",
    "back": "ינאי",
    "listId": "h1",
    "bucket": 1,
    "starred": false
  },
  {
    "id": "18",
    "type": "image",
    "front": "/game-images/img18.jpg",
    "back": "סופיה",
    "listId": "h1",
    "bucket": 1,
    "starred": false
  },
  {
    "id": "19",
    "type": "image",
    "front": "/game-images/img19.jpg",
    "back": "רומי",
    "listId": "h1",
    "bucket": 1,
    "starred": false
  },
  {
    "id": "20",
    "type": "image",
    "front": "/game-images/img20.jpg",
    "back": "דן",
    "listId": "h1",
    "bucket": 1,
    "starred": false
  }
]